werkflow_git/__init__.py
werkflow_git/git.py
werkflow_git-0.2.0.dist-info/licenses/LICENSE
werkflow_git-0.2.0.dist-info/METADATA
werkflow_git-0.2.0.dist-info/WHEEL
werkflow_git-0.2.0.dist-info/top_level.txt
werkflow_git-0.2.0.dist-info/RECORD
